Metadata-Version: 2.1
Name: lsm303-python
Version: 1.0.0
Summary: Python library for the LSM303 I2C accelerometer/magnetometer
Home-page: https://github.com/jackw01/lsm303-python
Author: jackw01
License: MIT
Platform: UNKNOWN
Classifier: License :: OSI Approved :: MIT License
Classifier: Programming Language :: Python
Classifier: Programming Language :: Python :: 3
Classifier: Programming Language :: Python :: Implementation :: CPython
Classifier: Programming Language :: Python :: Implementation :: PyPy
Requires-Python: >=3.7.0
